easypipinstall/__init__.py
easypipinstall/install.py
easypipinstall/version.py
easypipinstall-0.2.1.dist-info/LICENSE
easypipinstall-0.2.1.dist-info/METADATA
easypipinstall-0.2.1.dist-info/WHEEL
easypipinstall-0.2.1.dist-info/entry_points.txt
easypipinstall-0.2.1.dist-info/top_level.txt
easypipinstall-0.2.1.dist-info/RECORD
