Metadata-Version: 2.1
Name: easypipinstall
Version: 0.2.1
Summary: easypipinstall installs Python packages similarly to NPM in NodeJS. It automatically maintains the `requirements.txt`, `prod-requirements.txt` and `setup.cfg` files. It also easily uninstalls all the dependencies from those files.
Home-page: https://github.com/nicolasdao/easypipinstall
Author: Nicolas Dao
Author-email: nicolas.dao@gmail.com
License: BSD-3-Clause
Keywords: pip,install,uninstall
Classifier: Programming Language :: Python :: 3
Classifier: License :: OSI Approved :: BSD License
Requires-Python: >=3.7
License-File: LICENSE
Provides-Extra: dev
Requires-Dist: build ; extra == 'dev'
Requires-Dist: black ; extra == 'dev'
Requires-Dist: flake8 ; extra == 'dev'
Requires-Dist: twine ; extra == 'dev'
